pyinstapaper/__init__.py
pyinstapaper/instapaper.py
readwise_pyinstapaper-0.2.3.dist-info/DESCRIPTION.rst
readwise_pyinstapaper-0.2.3.dist-info/METADATA
readwise_pyinstapaper-0.2.3.dist-info/RECORD
readwise_pyinstapaper-0.2.3.dist-info/WHEEL
readwise_pyinstapaper-0.2.3.dist-info/metadata.json
readwise_pyinstapaper-0.2.3.dist-info/top_level.txt
