Metadata-Version: 2.0
Name: readwise-pyinstapaper
Version: 0.2.3
Summary: PyInstapaper is a Python wrapper for the full Instapaper API.
Home-page: https://github.com/mdorn/pyinstapaper
Author: Matt Dorn
Author-email: matt.dorn@gmail.com
License: MIT license
Keywords: pyinstapaper
Platform: UNKNOWN
Classifier: Development Status :: 2 - Pre-Alpha
Classifier: Intended Audience :: Developers
Classifier: License :: OSI Approved :: MIT License
Classifier: Natural Language :: English
Classifier: Programming Language :: Python :: 2
Classifier: Programming Language :: Python :: 2.7
Classifier: Programming Language :: Python :: 3
Classifier: Programming Language :: Python :: 3.4
Classifier: Programming Language :: Python :: 3.5
Classifier: Programming Language :: Python :: 3.6
Requires-Dist: future
Requires-Dist: httplib2 (>=0.9)
Requires-Dist: lxml (>=4)
Requires-Dist: oauth2 (<2,>=1.9)
Requires-Dist: requests (<3,>=2.7)
